flakestorm/__init__.py
flakestorm/assertions/__init__.py
flakestorm/assertions/deterministic.py
flakestorm/assertions/safety.py
flakestorm/assertions/semantic.py
flakestorm/assertions/verifier.py
flakestorm/cli/__init__.py
flakestorm/cli/main.py
flakestorm/core/__init__.py
flakestorm/core/config.py
flakestorm/core/orchestrator.py
flakestorm/core/performance.py
flakestorm/core/protocol.py
flakestorm/core/runner.py
flakestorm/integrations/__init__.py
flakestorm/integrations/embeddings.py
flakestorm/integrations/huggingface.py
flakestorm/mutations/__init__.py
flakestorm/mutations/engine.py
flakestorm/mutations/templates.py
flakestorm/mutations/types.py
flakestorm/reports/__init__.py
flakestorm/reports/html.py
flakestorm/reports/json_export.py
flakestorm/reports/models.py
flakestorm/reports/terminal.py
flakestorm-0.9.1.dist-info/METADATA
flakestorm-0.9.1.dist-info/WHEEL
flakestorm-0.9.1.dist-info/entry_points.txt
flakestorm-0.9.1.dist-info/licenses/LICENSE
flakestorm-0.9.1.dist-info/RECORD
