Metadata-Version: 2.4
Name: flakestorm
Version: 0.9.1
Summary: The Agent Reliability Engine - Chaos Engineering for AI Agents
Project-URL: Homepage, https://github.com/flakestorm/flakestorm
Project-URL: Documentation, https://flakestorm.dev/docs
Project-URL: Repository, https://github.com/flakestorm/flakestorm
Project-URL: Issues, https://github.com/flakestorm/flakestorm/issues
Author: flakestorm Team
License-Expression: Apache-2.0
License-File: LICENSE
Keywords: adversarial-testing,agents,ai,chaos-engineering,fuzzing,llm,reliability,testing
Classifier: Development Status :: 5 - Production/Stable
Classifier: Environment :: Console
Classifier: Intended Audience :: Developers
Classifier: License :: OSI Approved :: Apache Software License
Classifier: Operating System :: OS Independent
Classifier: Programming Language :: Python :: 3
Classifier: Programming Language :: Python :: 3.10
Classifier: Programming Language :: Python :: 3.11
Classifier: Programming Language :: Python :: 3.12
Classifier: Topic :: Scientific/Engineering :: Artificial Intelligence
Classifier: Topic :: Software Development :: Testing
Requires-Python: >=3.10
Requires-Dist: aiofiles>=23.0.0
Requires-Dist: httpx>=0.25.0
Requires-Dist: jinja2>=3.1.0
Requires-Dist: ollama>=0.3.0
Requires-Dist: pydantic-settings>=2.0.0
Requires-Dist: pydantic>=2.0.0
Requires-Dist: pyyaml>=6.0
Requires-Dist: rich>=13.0.0
Requires-Dist: typer>=0.9.0
Provides-Extra: all
Requires-Dist: black>=23.0.0; extra == 'all'
Requires-Dist: huggingface-hub>=0.19.0; extra == 'all'
Requires-Dist: maturin>=1.4.0; extra == 'all'
Requires-Dist: mypy>=1.0.0; extra == 'all'
Requires-Dist: numpy>=1.24.0; extra == 'all'
Requires-Dist: pre-commit>=3.0.0; extra == 'all'
Requires-Dist: pytest-asyncio>=0.21.0; extra == 'all'
Requires-Dist: pytest-cov>=4.0.0; extra == 'all'
Requires-Dist: pytest>=7.0.0; extra == 'all'
Requires-Dist: ruff>=0.1.0; extra == 'all'
Requires-Dist: sentence-transformers>=2.2.0; extra == 'all'
Provides-Extra: dev
Requires-Dist: black>=23.0.0; extra == 'dev'
Requires-Dist: maturin>=1.4.0; extra == 'dev'
Requires-Dist: mypy>=1.0.0; extra == 'dev'
Requires-Dist: pre-commit>=3.0.0; extra == 'dev'
Requires-Dist: pytest-asyncio>=0.21.0; extra == 'dev'
Requires-Dist: pytest-cov>=4.0.0; extra == 'dev'
Requires-Dist: pytest>=7.0.0; extra == 'dev'
Requires-Dist: ruff>=0.1.0; extra == 'dev'
Provides-Extra: huggingface
Requires-Dist: huggingface-hub>=0.19.0; extra == 'huggingface'
Provides-Extra: semantic
Requires-Dist: numpy>=1.24.0; extra == 'semantic'
Requires-Dist: sentence-transformers>=2.2.0; extra == 'semantic'
